lum/__init__.py
lum/api.py
lum/assembly.py
lum/config.py
lum/data.py
lum/github.py
lum/gitignore.py
lum/main.py
lum/smart_read.py
lum/visualizer.py
pylumen-2.0.0.dist-info/licenses/LICENSE
pylumen-2.0.0.dist-info/METADATA
pylumen-2.0.0.dist-info/WHEEL
pylumen-2.0.0.dist-info/entry_points.txt
pylumen-2.0.0.dist-info/top_level.txt
pylumen-2.0.0.dist-info/RECORD
