Metadata-Version: 2.4
Name: pylumen
Version: 2.0.0
Summary: The official CLI for the Lumen Protocol & Local Prompt Generation.
Home-page: https://github.com/Far3000-YT/lumen
Author: Far3k
Author-email: far3000yt@gmail.com
License: MIT
Classifier: Programming Language :: Python :: 3
Classifier: Programming Language :: Python :: 3.7
Classifier: Programming Language :: Python :: 3.8
Classifier: Programming Language :: Python :: 3.9
Classifier: Programming Language :: Python :: 3.10
Classifier: Programming Language :: Python :: 3.11
Classifier: Programming Language :: Python :: 3.12
Classifier: Programming Language :: Python :: 3.13
Classifier: License :: OSI Approved :: MIT License
Classifier: Operating System :: OS Independent
Requires-Python: >=3.7
License-File: LICENSE
Requires-Dist: requests
Requires-Dist: pyperclip
Requires-Dist: chardet
Requires-Dist: tiktoken
Requires-Dist: colorama
Requires-Dist: Pygments
Requires-Dist: websockets
Requires-Dist: scrubadub
Requires-Dist: trufflehog3
Dynamic: author
Dynamic: author-email
Dynamic: classifier
Dynamic: description
Dynamic: description-content-type
Dynamic: home-page
Dynamic: license
Dynamic: license-file
Dynamic: requires-dist
Dynamic: requires-python
Dynamic: summary
